odoo/addons/profiler/README.rst
odoo/addons/profiler/__init__.py
odoo/addons/profiler/__manifest__.py
odoo/addons/profiler/hooks.py
odoo/addons/profiler/i18n/es.po
odoo/addons/profiler/i18n/it.po
odoo/addons/profiler/i18n/profiler.pot
odoo/addons/profiler/models/__init__.py
odoo/addons/profiler/models/profiler_profile.py
odoo/addons/profiler/readme/CONTRIBUTORS.rst
odoo/addons/profiler/readme/DESCRIPTION.rst
odoo/addons/profiler/readme/INSTALL.rst
odoo/addons/profiler/readme/USAGE.rst
odoo/addons/profiler/security/ir.model.access.csv
odoo/addons/profiler/static/description/icon.png
odoo/addons/profiler/static/description/index.html
odoo/addons/profiler/tests/__init__.py
odoo/addons/profiler/tests/test_profiling.py
odoo/addons/profiler/views/profiler_profile_view.xml
odoo14_addon_profiler-14.0.1.0.1.dev8.dist-info/METADATA
odoo14_addon_profiler-14.0.1.0.1.dev8.dist-info/WHEEL
odoo14_addon_profiler-14.0.1.0.1.dev8.dist-info/top_level.txt
odoo14_addon_profiler-14.0.1.0.1.dev8.dist-info/RECORD
